best/__init__.py
best/integration/__init__.py
best/unit/__init__.py
best/unit/conftest.py
best/unit/test_glue_session.py
best/unit/test_glue_session_demo.py
best/unit/test_session_apis.py
pango-0.7.6.dist-info/LICENSE.txt
pango-0.7.6.dist-info/METADATA
pango-0.7.6.dist-info/WHEEL
pango-0.7.6.dist-info/top_level.txt
pango-0.7.6.dist-info/RECORD
